[
  { "name": "بيانكو قنا", "rating": 3.9, "reviews": 94, "phone": "01005687470", "address": "5P5C+QV9، شارع الجمهورية، قنا", "working_hours": "يغلق 11 م", "tags": "ملابس,ماركة", "lat": 26.159406, "lng": 32.7222207, "city": "قنا" },
  { "name": "بلبن - Bulbul", "rating": 4.3, "reviews": 46, "address": "23 يوليو، قنا", "working_hours": "يغلق 3 ص", "tags": "آيس كريم,حلويات", "lat": 26.1586421, "lng": 32.7177804, "city": "قنا" },
  { "name": "تاي هاوس Tie House", "rating": 4.2, "reviews": 112, "phone": "0963336099", "address": "وسط البلد، قنا", "working_hours": "يغلق 10 م", "tags": "ملابس رجالي", "lat": 26.1633073, "lng": 32.7084882, "city": "قنا" },
  { "name": "الملكة قنا", "rating": 5.0, "reviews": 1, "phone": "01064840010", "address": "شارع المنطقة التعليمية، مصطفى كامل، قنا", "working_hours": "يغلق 11 م", "tags": "ملابس حريمي,توصيل", "city": "قنا" },
  { "name": "المخزنجي - قنا", "rating": 4.0, "reviews": 91, "phone": "01092299740", "address": "5P38+68F، التحرير", "working_hours": "يغلق 10 م", "tags": "متجر متنوع", "lat": 26.1530728, "lng": 32.7157959, "city": "قنا" },
  { "name": "تاون تيم Town Team", "rating": 4.1, "reviews": 273, "phone": "01226065405", "address": "الجمهورية، قنا", "working_hours": "يغلق 9 م", "tags": "ملابس رجالي", "lat": 26.1593229, "lng": 32.7224707, "city": "قنا" },
  { "name": "Men's Club", "rating": 4.3, "reviews": 44, "address": "5P6F+4HR، قنا", "working_hours": "يغلق 1 ص", "tags": "ملابس رجالي", "lat": 26.1603604, "lng": 32.7238947, "city": "قنا" },
  { "name": "سنتر سوق قنا", "rating": 4.2, "reviews": 53, "phone": "01023867315", "address": "5P49+PHR", "tags": "سلع منزلية", "city": "قنا" },
  { "name": "ديرني لاند - Family Mall", "rating": 4.0, "reviews": 866, "phone": "01006895333", "working_hours": "يغلق 10 م", "tags": "ملابس أطفال", "city": "قنا" },
  { "name": "بنزايون - قنا", "rating": 3.8, "reviews": 2085, "phone": "0963320283", "address": "5P5C+FVF، بورسعيد، قنا", "working_hours": "يغلق 11 م", "tags": "متجر شامل,أسعار", "is_featured": true, "city": "قنا" },
  { "name": "Al Kamal Mall - الكمال مول", "rating": 4.4, "reviews": 54, "phone": "01012500400", "address": "5P6G+C8J، الجمهورية، قنا", "working_hours": "يغلق 11 م", "tags": "مركز تسوق,مول", "is_featured": true, "city": "قنا" },
  { "name": "محل براند BRAND قنا", "rating": 5.0, "reviews": 1, "phone": "01007730681", "address": "5P49+VC5، قنا", "working_hours": "يغلق 10 م", "tags": "ملابس حريمي", "city": "قنا" },
  { "name": "دراك ستور Dark Store", "rating": 4.1, "reviews": 47, "address": "هلالي، قسم قنا", "working_hours": "يغلق 10 م", "tags": "أحذية", "city": "قنا" },
  { "name": "ماركت آخر ساعة", "rating": 4.2, "reviews": 432, "address": "5PFJ+WQ3", "working_hours": "يغلق 2 ص", "tags": "سوبرماركت,24 ساعة", "city": "قنا" },
  { "name": "سنتر الوعي الإسلامي", "rating": 4.3, "reviews": 150, "phone": "01118026788", "address": "5P8C+48W، آخر شارع بي تك", "working_hours": "يغلق 12 ص", "tags": "ملابس,زي إسلامي,محتشم", "city": "قنا" },
  { "name": "بيلا مود الرجالي", "rating": 3.9, "reviews": 44, "phone": "0963333636", "address": "5P5C+6HJ، مصطفى كامل، قنا", "tags": "ملابس رجالي", "city": "قنا" },
  { "name": "يحيى النني للمحمول", "rating": 4.6, "reviews": 24, "phone": "01017872787", "address": "الجمهورية، قسم قنا", "working_hours": "24 ساعة", "tags": "موبايل,صيانة,24 ساعة", "city": "قنا" },
  { "name": "Van dutti", "rating": 4.2, "reviews": 116, "working_hours": "يغلق 10 م", "tags": "ملابس", "city": "قنا" },
  { "name": "أتيلية الأسطورة - حوض 10", "rating": 4.1, "reviews": 73, "phone": "01003784990", "working_hours": "يغلق 4 م", "tags": "تأجير فساتين زفاف", "city": "قنا" },
  { "name": "سنتر الجويلي", "rating": 4.5, "reviews": 64, "phone": "01010757181", "address": "ميدان بنزيون، الأقصر، قنا", "working_hours": "يغلق 10 م", "tags": "مركز تسوق,ملابس", "is_featured": true, "city": "قنا" },
  { "name": "وشاحي تكس - أقمشة ومفروشات", "rating": 4.3, "reviews": 16, "address": "5P69+3G3، السوق الفقاني", "working_hours": "يغلق 10 م", "tags": "أقمشة,مفروشات", "city": "قنا" },
  { "name": "أكتيف ابو علاء - فرع قنا", "rating": 4.4, "reviews": 5, "phone": "01032301008", "address": "5P6G+95M، الجمهورية، قنا", "working_hours": "يغلق 11 م", "tags": "ملابس رياضية", "city": "قنا" },
  { "name": "Barghout برغوت - حلويات", "rating": 4.5, "reviews": 41, "phone": "01228180709", "address": "الجمهورية، قنا", "working_hours": "يغلق 11 م", "tags": "حلويات,توصيل", "city": "قنا" },
  { "name": "مول خان خليفة قنا", "rating": 4.6, "reviews": 9, "address": "ميدان بنزايون، خلف بيانكو، قنا", "tags": "عطارة,متجر عمومي", "city": "قنا" },
  { "name": "بي تك قنا - B.TECH", "rating": 3.9, "reviews": 932, "phone": "0223220621", "address": "الشنهورية، قنا", "working_hours": "يغلق 10 م", "tags": "أجهزة إلكترونية,B.TECH", "is_featured": true, "city": "قنا" },
  { "name": "شوكة وسكينة للأدوات المنزلية", "rating": 3.5, "reviews": 17, "phone": "01157799909", "address": "5P6G+W34, Refaee B", "working_hours": "يغلق 11 م", "tags": "سلع منزلية,توصيل", "city": "قنا" },
  { "name": "كارينا Karina", "rating": 5.0, "reviews": 2, "phone": "01119754129", "address": "5P5C+54C، وسط البلد، قنا", "working_hours": "يغلق 11 م", "tags": "ملابس", "city": "قنا" },
  { "name": "وي فاشون للملابس الحريمي", "rating": 5.0, "reviews": 8, "phone": "01028885924", "address": "سوق ليبيا، قنا", "working_hours": "24 ساعة", "tags": "ملابس حريمي", "city": "قنا" },
  { "name": "الجويلي للملابس الجاهزة", "rating": 4.2, "reviews": 57, "phone": "01010757181", "address": "قنا - شارع سوق ليبيا", "working_hours": "24 ساعة", "tags": "ملابس شباب,ملابس", "city": "قنا" },
  { "name": "سنتر طقاطيق للأدوات المنزلية", "rating": 4.6, "reviews": 13, "phone": "01002154010", "address": "5P59+2VF, Al Qmas Yase", "working_hours": "24 ساعة", "tags": "سلع منزلية", "city": "قنا" },
  { "name": "قطونيل - فرع قنا", "rating": 5.0, "reviews": 3, "phone": "01000070351", "address": "23 يوليو - أمام بنك القاهرة / الكمال مول", "working_hours": "يغلق 11 م", "tags": "ملابس داخلية,توصيل", "city": "قنا" },
  { "name": "TOY STORE", "rating": 4.2, "reviews": 30, "phone": "01110022454", "address": "الجمهورية، قنا", "working_hours": "يغلق 11 م", "tags": "ألعاب,مركز تسوق", "city": "قنا" },
  { "name": "فضيات ليمار", "rating": 4.9, "reviews": 21, "phone": "01007630725", "address": "5P5F+H7F، وسط البلد، قنا", "working_hours": "يغلق 10 م", "tags": "مجوهرات,فضيات", "city": "قنا" },
  { "name": "Africa Store Qena", "rating": 4.9, "reviews": 11, "phone": "01012708270", "address": "5P44+WX2، قنا", "tags": "ملابس", "city": "قنا" },
  { "name": "SalmaStyle", "rating": 5.0, "reviews": 1, "phone": "01000456067", "address": "شارع مخبز المغربي، قنا", "working_hours": "24 ساعة", "tags": "ملابس حريمي", "city": "قنا" },
  { "name": "قنا محلات - متجر كتب", "rating": 5.0, "reviews": 1, "phone": "+447448183351", "address": "المحطة، قنا", "working_hours": "24 ساعة", "tags": "كتب", "city": "قنا" },
  { "name": "حبيبة للطباعة والهدايا", "rating": 4.1, "reviews": 21, "phone": "01003069338", "address": "الصفا والمروة، قنا", "working_hours": "يغلق 10 م", "tags": "هدايا,طباعة,توصيل", "city": "قنا" },
  { "name": "Toy Store - مصطفى كامل", "rating": 4.4, "reviews": 18, "phone": "01110022454", "address": "مصطفى كامل، قنا", "working_hours": "يغلق 11 م", "tags": "ألعاب", "city": "قنا" },
  { "name": "فاشون ستور قنا", "rating": 5.0, "reviews": 2, "address": "5P79+94H، الشنهورية", "tags": "ملابس", "city": "قنا" },
  { "name": "سنتر شاهين للمفروشات", "rating": 4.5, "reviews": 15, "phone": "01010290006", "address": "5P79+P7R، هاشم الدقيني", "working_hours": "يغلق 11 م", "tags": "مفروشات,لحف", "city": "قنا" },
  { "name": "الحبيب ماركت", "rating": 4.2, "reviews": 1966, "phone": "0963324222", "address": "المديرية، قنا", "working_hours": "يغلق 2 ص", "tags": "ملابس,هايبر", "is_featured": true, "city": "قنا" },
  { "name": "محلات البطل للحدايد والبويات", "rating": 4.3, "reviews": 20, "phone": "01202000366", "address": "5PCF+MX5", "tags": "حدايد,بويات", "city": "قنا" },
  { "name": "سمارت فيرنيتشر - سمارت لايف", "rating": 3.9, "reviews": 111, "phone": "0219641", "address": "طريق الرياح، قنا", "working_hours": "يغلق 10 م", "tags": "أثاث", "city": "قنا" },
  { "name": "Zoom Eyes Qena - زووم آيز", "rating": 3.8, "reviews": 21, "phone": "01000770708", "address": "أمام الممشى التجاري، 23 يوليو", "working_hours": "يغلق 11 م", "tags": "بصريات,نظارات", "city": "قنا" },
  { "name": "UH TECH Hikvision Qena", "rating": 4.8, "reviews": 36, "phone": "01000730004", "address": "بجوار كنتاكي، الجمهورية، قنا", "working_hours": "يغلق 10:30 م", "tags": "إلكترونيات,كاميرات مراقبة,Hikvision", "city": "قنا" },
  { "name": "كباية للأدوات المنزلية", "rating": 4.0, "reviews": 7, "phone": "01063461937", "address": "خلف عمر أفندي، قنا", "working_hours": "يغلق 11 م", "tags": "سلع منزلية", "city": "قنا" },
  { "name": "CANON العالمية قنا", "rating": 4.0, "reviews": 151, "phone": "01050662760", "address": "شارع كوبري أمام مستشفى العام، قنا", "working_hours": "يغلق 10 م", "tags": "طابعات,أجهزة", "city": "قنا" },
  { "name": "فريسيا 2 - زهور", "rating": 4.5, "reviews": 17, "phone": "01022344312", "address": "الجمهورية، قنا", "working_hours": "يغلق 10 م", "tags": "زهور,ورد", "city": "قنا" },
  { "name": "Party Store", "rating": 4.3, "reviews": 3, "phone": "01095641025", "address": "5P49+XF6، شارع جينودي", "working_hours": "يغلق 10 م", "tags": "هدايا,حفلات", "city": "قنا" },
  { "name": "بيلا ميكاب - مستحضرات تجميل", "rating": 5.0, "reviews": 9, "phone": "01010718842", "address": "5P59+4RH، مول مدينتي", "tags": "مستحضرات تجميل,عطور", "city": "قنا" },
  { "name": "لولي قنا", "rating": 5.0, "reviews": 1, "phone": "01024251640", "address": "موقف سيارات، نجع حمادي - دشنا", "tags": "ملابس", "city": "نجع حمادي" },
  { "name": "Otp Apple Store", "rating": 4.5, "reviews": 4, "phone": "01552710028", "address": "26 يوليو، أمام نادي ضباط الشرطة، قنا", "working_hours": "يغلق 11 م", "tags": "موبايل,أبل", "city": "قنا" },
  { "name": "قطونيل - الفرع الرئيسي", "rating": 4.5, "reviews": 18, "phone": "01014486600", "address": "23 يوليو، أمام بنك القاهرة، قنا", "working_hours": "يغلق 11 م", "tags": "ملابس داخلية نسائية", "city": "قنا" },
  { "name": "حلواني الفردوس", "rating": 3.9, "reviews": 68, "phone": "01010305005", "address": "5PHM+4M5", "working_hours": "24 ساعة", "tags": "حلويات,24 ساعة", "city": "قنا" },
  { "name": "Happy Maker - آيس كريم", "rating": 4.8, "reviews": 12, "address": "مسجد التحرير، 26 يوليو، قنا", "working_hours": "يغلق 2 ص", "tags": "آيس كريم,حلويات", "city": "قنا" },
  { "name": "بيلا شوز - Bella Shoes", "rating": 3.7, "reviews": 87, "address": "5P5C+55F، مصطفى كامل، قنا", "tags": "أحذية", "city": "قنا" },
  { "name": "Dr. KiD", "rating": 5.0, "reviews": 10, "phone": "01024709686", "address": "المنطقة التعليمية، قسم قنا", "working_hours": "يغلق 11 م", "tags": "ملابس أطفال", "city": "قنا" },
  { "name": "Elegant Store", "rating": 5.0, "reviews": 1, "phone": "01224283535", "address": "شارع المأمور أمام بنك ناصر، قنا", "tags": "ملابس حريمي,توصيل", "city": "قنا" },
  { "name": "هشام وقوق للأدوات المنزلية", "rating": 5.0, "reviews": 2, "phone": "01006622480", "address": "مصنع المكرونة، قنا", "working_hours": "يغلق 12 ص", "tags": "سلع منزلية", "city": "قنا" },
  { "name": "لحوم الجزار", "rating": 4.6, "reviews": 15, "phone": "01128450012", "address": "5P4C+333", "working_hours": "يغلق 10 م", "tags": "لحوم,ملحمة,توصيل", "city": "قنا" },
  { "name": "آدم ستور - كتب", "rating": 4.7, "reviews": 3, "phone": "01007040428", "working_hours": "يغلق 11 م", "tags": "كتب,مكتبة", "city": "قنا" },
  { "name": "HUB Furniture", "rating": 4.2, "reviews": 37, "phone": "01111233356", "address": "امتداد كوبري دندرة، بجوار مستشفى قنا العام", "working_hours": "يغلق 10 م", "tags": "أثاث", "city": "قنا" },
  { "name": "محلات النور", "rating": 4.3, "reviews": 4, "phone": "01007671699", "address": "23 يوليو، قنا", "working_hours": "يغلق 11 م", "tags": "ملابس", "city": "قنا" },
  { "name": "فرع أورنج بقنا Orange", "rating": 3.6, "reviews": 66, "phone": "01223202020", "working_hours": "يغلق 10 م", "tags": "موبايل,اتصالات,أورنج", "city": "قنا" },
  { "name": "أتيلية دانتيلا - فساتين زفاف", "rating": 3.5, "reviews": 4, "phone": "01207695669", "address": "5P39+J58، بورسعيد، قنا", "working_hours": "24 ساعة", "tags": "فساتين زفاف,خطوبة", "city": "قنا" },
  { "name": "مكتب الجوازات - قنا", "rating": 3.7, "reviews": 128, "phone": "0965210408", "working_hours": "يغلق 2:45 م", "tags": "جوازات سفر,حكومي", "city": "قنا" },
  { "name": "2pánky - أحذية", "rating": 5.0, "reviews": 1, "phone": "01030444150", "address": "سنتر جنودي، قنا - إدفو", "working_hours": "يغلق 1:30 ص", "tags": "أحذية", "city": "قنا" },
  { "name": "أجواء Agwaa", "rating": 4.1, "reviews": 8, "phone": "01026291044", "address": "5P79+JH4، هاشم الدقيني", "working_hours": "يغلق 11 م", "tags": "ملابس حريمي,توصيل", "city": "قنا" },
  { "name": "هاي هوم قنا Hi Home - أثاث", "rating": 3.0, "reviews": 3, "phone": "01125667612", "tags": "أثاث منزلي", "city": "قنا" },
  { "name": "سيرا قنا", "rating": 4.5, "reviews": 2, "phone": "01095033611", "address": "5P75+424", "tags": "سلع منزلية,توصيل", "city": "قنا" },
  { "name": "Farag Sport", "rating": 5.0, "reviews": 3, "phone": "01025906008", "address": "5P7F+FPG، قسم قنا", "working_hours": "يغلق 10 م", "tags": "ملابس رياضية", "city": "قنا" },
  { "name": "Polo - ملابس", "rating": 5.0, "reviews": 2, "phone": "01113434295", "address": "5P6G+F73، شارع الجميل، ميدان الكمال، قنا", "working_hours": "يغلق 10 م", "tags": "ملابس شباب,بولو", "city": "قنا" },
  { "name": "Samsung Brand Store Qena", "rating": 3.5, "reviews": 76, "phone": "01012900200", "address": "مول الكمال، الجمهورية، قنا", "working_hours": "يغلق 9 م", "tags": "سامسونج,إلكترونيات", "city": "قنا" },
  { "name": "حلواني الشيف", "rating": 4.1, "reviews": 351, "phone": "0963320321", "address": "5P58+CHM", "price_range": "$$", "tags": "حلويات", "city": "قنا" },
  { "name": "مخابز علي مبارك", "rating": 4.4, "reviews": 34, "phone": "0963226311", "address": "5PGJ+8X5، قنا-الشئون، أمام التجنيد", "working_hours": "24 ساعة", "tags": "مخبز,24 ساعة", "city": "قنا" },
  { "name": "محلات سندريلا الجربوعي", "rating": 4.4, "reviews": 10, "phone": "01000272757", "address": "ميدان الجبلاوي، قسم قنا", "tags": "ملابس,توصيل", "city": "قنا" },
  { "name": "أيس كريم الفيروز", "rating": 4.3, "reviews": 59, "phone": "01027071990", "working_hours": "يغلق 1:30 ص", "tags": "آيس كريم,ألبان", "city": "قنا" },
  { "name": "محل OData", "rating": 4.8, "reviews": 4, "address": "5P79+Q87، هاشم الدقيني", "tags": "أجهزة إلكترونية", "city": "قنا" }
]
